rocketmq/__init__.py
rocketmq/client.py
rocketmq/consts.py
rocketmq/exceptions.py
rocketmq/ffi.py
rocketmq/librocketmq.dylib
rocketmq-0.4.4.dist-info/LICENSE
rocketmq-0.4.4.dist-info/METADATA
rocketmq-0.4.4.dist-info/WHEEL
rocketmq-0.4.4.dist-info/top_level.txt
rocketmq-0.4.4.dist-info/RECORD
