Metadata-Version: 2.1
Name: rocketmq
Version: 0.4.4
Summary: RocketMQ Python client
Home-page: UNKNOWN
Author: messense
Author-email: messense@icloud.com
License: UNKNOWN
Keywords: rocketmq
Platform: UNKNOWN
Classifier: Operating System :: MacOS
Classifier: Operating System :: POSIX
Classifier: Operating System :: POSIX :: Linux
Classifier: Programming Language :: Python
Classifier: Programming Language :: Python :: 2.7
Classifier: Programming Language :: Python :: 3.5
Classifier: Programming Language :: Python :: 3.6
Classifier: Programming Language :: Python :: 3.7
Classifier: Programming Language :: Python :: Implementation :: CPython
Requires-Dist: enum34 ; python_version <= "3.4"
